django_time_block/__about__.py
django_time_block/__init__.py
django_time_block/admin.py
django_time_block/apps.py
django_time_block/models.py
django_time_block/tests.py
django_time_block/utils.py
django_time_block/views.py
django_time_block/migrations/0001_initial.py
django_time_block/migrations/0002_alter_timeblock_object_id_and_more.py
django_time_block/migrations/0003_timeblock_django_time_object__7ce4e8_idx.py
django_time_block/migrations/0004_relationtimeblock.py
django_time_block/migrations/0005_relationtimeblock_update_datetime_and_more.py
django_time_block/migrations/__init__.py
django_time_block-0.5.0.dist-info/METADATA
django_time_block-0.5.0.dist-info/WHEEL
django_time_block-0.5.0.dist-info/licenses/LICENSE
django_time_block-0.5.0.dist-info/licenses/LICENSE.txt
django_time_block-0.5.0.dist-info/RECORD
