Metadata-Version: 2.1
Name: django-time-block
Version: 0.5.0
Project-URL: Documentation, https://github.com/ramwin/django-time-block#readme
Project-URL: Issues, https://github.com/ramwin/django-time-block/issues
Project-URL: Source, https://github.com/ramwin/django-time-block
Author-email: Xiang Wang <ramwin@qq.com>
License-Expression: MIT
License-File: LICENSE
License-File: LICENSE.txt
Classifier: Development Status :: 4 - Beta
Classifier: Programming Language :: Python
Classifier: Programming Language :: Python :: 3.7
Classifier: Programming Language :: Python :: 3.8
Classifier: Programming Language :: Python :: 3.9
Classifier: Programming Language :: Python :: 3.10
Classifier: Programming Language :: Python :: 3.11
Classifier: Programming Language :: Python :: Implementation :: CPython
Classifier: Programming Language :: Python :: Implementation :: PyPy
Requires-Python: >=3.7
Requires-Dist: django
